bibt/gcp/storage/__init__.py
bibt/gcp/storage/classes.py
bibt/gcp/storage/methods.py
bibt/gcp/storage/params.py
bibt/gcp/storage/version.py
bibt_gcp_storage-0.0.15.dist-info/METADATA
bibt_gcp_storage-0.0.15.dist-info/WHEEL
bibt_gcp_storage-0.0.15.dist-info/licenses/LICENSE
bibt_gcp_storage-0.0.15.dist-info/RECORD
