Metadata-Version: 2.4
Name: bibt-gcp-storage
Version: 0.0.15
Summary: Functionality often used by BITS Blue Team (GCP GCS).
Project-URL: Bug Tracker, https://github.com/broadinstitute/bibt-gcp-storage/issues
Project-URL: Documentation, https://bibt-gcp-storage.readthedocs.io/en/latest/
Project-URL: Homepage, https://github.com/broadinstitute/bibt-gcp-storage
Author-email: Matthew OBrien <mobrien@broadinstitute.org>
License-File: LICENSE
Classifier: License :: OSI Approved :: MIT License
Classifier: Operating System :: OS Independent
Classifier: Programming Language :: Python :: 3
Classifier: Programming Language :: Python :: 3.9
Classifier: Programming Language :: Python :: 3.10
Classifier: Programming Language :: Python :: 3.11
Classifier: Programming Language :: Python :: 3.12
Classifier: Topic :: Security
Classifier: Topic :: Software Development :: Libraries
Classifier: Topic :: Utilities
Requires-Python: >=3.7
Requires-Dist: google-cloud-storage==2.14.0
